how_long_flameai/__init__.py
how_long_flameai/how_long.py
how_long_flameai-0.1.1.dist-info/WHEEL
how_long_flameai-0.1.1.dist-info/METADATA
how_long_flameai-0.1.1.dist-info/RECORD
