Metadata-Version: 2.1
Name: how-long-flameai
Version: 0.1.1
Summary: 
Author: Your Name
Author-email: you@example.com
Requires-Python: >=3.9,<4.0
Classifier: Programming Language :: Python :: 3
Classifier: Programming Language :: Python :: 3.9
Requires-Dist: coo (>=0.1.3,<0.2.0)
Requires-Dist: pendulum (>=2.1.2,<3.0.0)
